{
	"configurations" : 
	[
		{
			"directories" : 
			[
				{
					"build" : ".",
					"hasInstallRule" : true,
					"jsonFile" : "directory-.-7e5a2b92fa3cb7e52336.json",
					"minimumCMakeVersion" : 
					{
						"string" : "3.12"
					},
					"projectIndex" : 0,
					"source" : ".",
					"targetIndexes" : 
					[
						0,
						1
					]
				}
			],
			"name" : "",
			"projects" : 
			[
				{
					"directoryIndexes" : 
					[
						0
					],
					"name" : "sweepy_nav",
					"targetIndexes" : 
					[
						0,
						1
					]
				}
			],
			"targets" : 
			[
				{
					"directoryIndex" : 0,
					"id" : "sweepy_nav_uninstall::@6890427a1f51a3e7e1df",
					"jsonFile" : "target-sweepy_nav_uninstall-b87c97b3b9bfc4bca146.json",
					"name" : "sweepy_nav_uninstall",
					"projectIndex" : 0
				},
				{
					"directoryIndex" : 0,
					"id" : "uninstall::@6890427a1f51a3e7e1df",
					"jsonFile" : "target-uninstall-d342b022e93bce0cd5d8.json",
					"name" : "uninstall",
					"projectIndex" : 0
				}
			]
		}
	],
	"kind" : "codemodel",
	"paths" : 
	{
		"build" : "/home/robot/sweepy_dev_ws/build/sweepy_nav",
		"source" : "/home/robot/sweepy_dev_ws/src/sweepy_nav"
	},
	"version" : 
	{
		"major" : 2,
		"minor" : 3
	}
}
